odoo/addons/sale_commission_salesman/README.rst
odoo/addons/sale_commission_salesman/__init__.py
odoo/addons/sale_commission_salesman/__manifest__.py
odoo/addons/sale_commission_salesman/i18n/es.po
odoo/addons/sale_commission_salesman/i18n/es_AR.po
odoo/addons/sale_commission_salesman/i18n/sale_commission_salesman.pot
odoo/addons/sale_commission_salesman/models/__init__.py
odoo/addons/sale_commission_salesman/models/account_move.py
odoo/addons/sale_commission_salesman/models/res_partner.py
odoo/addons/sale_commission_salesman/models/sale_order.py
odoo/addons/sale_commission_salesman/readme/CONFIGURE.rst
odoo/addons/sale_commission_salesman/readme/CONTRIBUTORS.rst
odoo/addons/sale_commission_salesman/readme/CREDITS.rst
odoo/addons/sale_commission_salesman/readme/DESCRIPTION.rst
odoo/addons/sale_commission_salesman/readme/USAGE.rst
odoo/addons/sale_commission_salesman/static/description/icon.png
odoo/addons/sale_commission_salesman/static/description/icon.svg
odoo/addons/sale_commission_salesman/static/description/index.html
odoo/addons/sale_commission_salesman/tests/__init__.py
odoo/addons/sale_commission_salesman/tests/test_sale_commission_salesman.py
odoo/addons/sale_commission_salesman/views/res_partner_views.xml
odoo13_addon_sale_commission_salesman-13.0.1.0.1.dist-info/METADATA
odoo13_addon_sale_commission_salesman-13.0.1.0.1.dist-info/WHEEL
odoo13_addon_sale_commission_salesman-13.0.1.0.1.dist-info/top_level.txt
odoo13_addon_sale_commission_salesman-13.0.1.0.1.dist-info/RECORD
